{"venkateshwara": {"password": "venky", "portfolios": [{"name": "p1", "balance": 148950.37783050537, "stocks": [{"stock": "MMM", "quantity": 23.0}, {"stock": "AXP", "quantity": 60.0}, {"stock": "AAPL", "quantity": 95.0}, {"stock": "BA", "quantity": 57.0}, {"stock": "CSCO", "quantity": 58.0}, {"stock": "DIS", "quantity": 81.0}, {"stock": "GE", "quantity": 32.0}, {"stock": "GS", "quantity": 84.0}, {"stock": "IBM", "quantity": 14.0}, {"stock": "JNJ", "quantity": 49.0}, {"stock": "MCD", "quantity": 12.0}, {"stock": "MSFT", "quantity": 80.0}, {"stock": "NKE", "quantity": 9.0}, {"stock": "PFE", "quantity": 47.0}, {"stock": "PG", "quantity": 55.0}, {"stock": "WMT", "quantity": 92.0}]}, {"name": "p2", "balance": 2022.1767387390137, "stocks": [{"stock": "MMM", "quantity": 11.0}, {"stock": "AXP", "quantity": 60.0}, {"stock": "AAPL", "quantity": 35.0}, {"stock": "INTC", "quantity": 1.0}]}, {"name": "p3", "balance": 1000.0, "stocks": []}]}, "shiva": {"password": "shiva", "portfolios": [{"name": "wer", "balance": 21.05290885925293, "stocks": [{"stock": "MMM", "quantity": 10.81}, {"stock": "CVX", "quantity": 1.0}]}]}}